hola_mundo/__init__.py
hola_mundo/main.py
hola_mundo_mercadona-0.0.1.dist-info/LICENSE
hola_mundo_mercadona-0.0.1.dist-info/METADATA
hola_mundo_mercadona-0.0.1.dist-info/WHEEL
hola_mundo_mercadona-0.0.1.dist-info/top_level.txt
hola_mundo_mercadona-0.0.1.dist-info/RECORD
