Metadata-Version: 2.1
Name: hola-mundo-mercadona
Version: 0.0.1
Summary: Mi primer Package subido a Pypi
Home-page: https://gitlab.com/masajo/mercadona-pypi
Author: Martín San José
Author-email: martin@imaginagroup.com
Maintainer: Martín San José
License: UNKNOWN
Platform: UNKNOWN
Classifier: Programming Language :: Python :: 3.8
Classifier: Operating System :: OS Independent
Classifier: License :: OSI Approved :: MIT License
Classifier: Intended Audience :: Developers
Requires-Python: >=3.6
